{
  "campaignId": "campaign_1772206235473",
  "figmaUrl": "https://www.figma.com/design/lIYVyJJuzmEZm13tkSDRn0/Signos-Campaign----Declare-Your-Food-Independence",
  "variants": [
    { "name": "Variant A — Bold", "exportPath": "generated-ads/campaign_1772206235473/variant-a-bold-1772206349320.png" },
    { "name": "Variant B — Clean", "exportPath": "generated-ads/campaign_1772206235473/variant-b-clean-1772206349320.png" }
  ],
  "caption": "This Independence Day, break free from the guesswork. 🇺🇸 While GLP-1s can jumpstart your journey, true freedom comes from understanding what YOUR body actually needs. Get real-time glucose insights that put you back in control of your health decisions. No more injection schedules. No more food anxiety. Just confident choices backed by your body's real data. Ready to graduate to true metabolic independence? #MetabolicFreedom #CGM #GLP1Graduate #HealthIndependence #SignosCGM #BiohackYourHealth #MenOver40 #WeightLossJourney",
  "timestamp": 1772206349320
}
